sos_java/__init__.py
sos_java/_version.py
sos_java/helper.jar
sos_java/kernel.py
sos_java-0.1.0.dist-info/LICENSE
sos_java-0.1.0.dist-info/METADATA
sos_java-0.1.0.dist-info/WHEEL
sos_java-0.1.0.dist-info/entry_points.txt
sos_java-0.1.0.dist-info/top_level.txt
sos_java-0.1.0.dist-info/RECORD
